plexus/common/__init__.py
plexus/common/pose.py
plexus/common/proj.py
plexus/common/carto/OSMFile.py
plexus/common/carto/OSMNode.py
plexus/common/carto/OSMTags.py
plexus/common/carto/OSMWay.py
plexus/common/carto/__init__.py
plexus/common/utils/__init__.py
plexus/common/utils/apiutils.py
plexus/common/utils/bagutils.py
plexus/common/utils/config.py
plexus/common/utils/datautils.py
plexus/common/utils/jsonutils.py
plexus/common/utils/ormutils.py
plexus/common/utils/s3utils.py
plexus/common/utils/shutils.py
plexus/common/utils/sqlutils.py
plexus/common/utils/strutils.py
plexus/common/utils/testutils.py
plexus_python_common-1.0.36.dist-info/METADATA
plexus_python_common-1.0.36.dist-info/WHEEL
plexus_python_common-1.0.36.dist-info/top_level.txt
plexus_python_common-1.0.36.dist-info/RECORD
