Metadata-Version: 2.4
Name: plexus-python-common
Version: 1.0.36
Classifier: Programming Language :: Python :: 3
Classifier: Programming Language :: Python :: 3.12
Classifier: Programming Language :: Python :: 3.13
Classifier: Programming Language :: Python :: 3.14
Requires-Python: <3.15,>=3.12
Requires-Dist: aiobotocore<2.27,>=2.26
Requires-Dist: boto3<1.42,>=1.41
Requires-Dist: boto3-stubs[s3]<1.42,>=1.41
Requires-Dist: fsspec>=2025.10
Requires-Dist: lxml>=6.0
Requires-Dist: numpy>=2.3
Requires-Dist: pydantic>=2.8
Requires-Dist: pygeodesy>=24.10
Requires-Dist: pyparsing>=3.2
Requires-Dist: pyproj>=3.6
Requires-Dist: pyquaternion>=0.9
Requires-Dist: sqlalchemy>=2.0
Requires-Dist: s3fs>=2025.10
Requires-Dist: rich>=13.9
Requires-Dist: textcase>=0.4
Requires-Dist: ujson>=5.9
Requires-Dist: iker-python-common[all]>=1.0
Provides-Extra: all
Requires-Dist: plexus-python-common[api]; extra == "all"
Provides-Extra: api
Requires-Dist: fastapi>=0.119.0; extra == "api"
Requires-Dist: sqlmodel>=0.0.25; extra == "api"
Provides-Extra: test
Requires-Dist: ddt>=1.7; extra == "test"
Requires-Dist: moto[s3,server]>=5.1; extra == "test"
Requires-Dist: pytest-cov>=5.0; extra == "test"
Requires-Dist: pytest-order>=1.3; extra == "test"
Requires-Dist: pytest-postgresql>=6.1; extra == "test"
Requires-Dist: pytest>=8.3; extra == "test"
